<annotation>
	<folder>putin</folder>
	<filename>путин-с-кулаком-640x394.jpg</filename>
	<path>D:\prog\labelimg\putin\путин-с-кулаком-640x394.jpg</path>
	<source>
		<database>Unknown</database>
	</source>
	<size>
		<width>640</width>
		<height>394</height>
		<depth>3</depth>
	</size>
	<segmented>0</segmented>
	<object>
		<name>Putin</name>
		<pose>Unspecified</pose>
		<truncated>0</truncated>
		<difficult>0</difficult>
		<bndbox>
			<xmin>142</xmin>
			<ymin>41</ymin>
			<xmax>322</xmax>
			<ymax>276</ymax>
		</bndbox>
	</object>
</annotation>
